{"type":"FeatureCollection","metadata":{"name":"Промышленные объекты","creator":"Yandex Map Constructor","description":"Список промышленных объектов"},"features":[{"type":"Feature","id":0,"geometry":{"coordinates":[60.14268036826934,56.84108642306679],"type":"Point"},"properties":{"description":"Объект складского назначения 5400 м2, пож. резервуары","iconCaption":"Складской комплекс","iconContent":"1","marker-color":"#1e98ff"}},{"type":"Feature","id":1,"geometry":{"coordinates":[59.96808465465346,56.89859651842441],"type":"Point"},"properties":{"description":"Реконструкция ИТП со строительством котельной 2 МВт","iconCaption":"ВимБильДан","iconContent":"2","marker-color":"#1e98ff"}},{"type":"Feature","id":2,"geometry":{"coordinates":[60.789328775250354,56.86971449463433],"type":"Point"},"properties":{"description":"Объект агропромышленного комплекса. Вертикальная клубничная ферма","iconCaption":"Ферма","iconContent":"3","marker-color":"#1e98ff"}},{"type":"Feature","id":3,"geometry":{"coordinates":[60.67262049659402,56.94650558259505],"type":"Point"},"properties":{"description":"Складская зона","iconCaption":"Склад 1500 м2","iconContent":"4","marker-color":"#1e98ff"}}]}